shareplumfreightplusio/__init__.py
shareplumfreightplusio/errors.py
shareplumfreightplusio/folder.py
shareplumfreightplusio/list.py
shareplumfreightplusio/list_dict.py
shareplumfreightplusio/office365.py
shareplumfreightplusio/request_helper.py
shareplumfreightplusio/site.py
shareplumfreightplusio/soap.py
shareplumfreightplusio/version.py
shareplumfreightplusio-0.5.3.dist-info/LICENSE.txt
shareplumfreightplusio-0.5.3.dist-info/METADATA
shareplumfreightplusio-0.5.3.dist-info/WHEEL
shareplumfreightplusio-0.5.3.dist-info/top_level.txt
shareplumfreightplusio-0.5.3.dist-info/RECORD
