Metadata-Version: 2.1
Name: shareplumfreightplusio
Version: 0.5.3
Summary: Python SharePoint FreightPlus Library
Home-page: https://github.com/rcwethey/shareplumFreightplusIO
Author: Ryan Wethey
Author-email: rwethey@freightplus.io
License: MIT
Keywords: SharePoint
Classifier: Development Status :: 4 - Beta
Classifier: License :: OSI Approved :: MIT License
Classifier: Programming Language :: Python
Classifier: Programming Language :: Python :: 3.6
Classifier: Programming Language :: Python :: 3.7
Classifier: Programming Language :: Python :: 3.8
Classifier: Intended Audience :: Developers
Classifier: Intended Audience :: Information Technology
Classifier: Intended Audience :: System Administrators
Classifier: Operating System :: OS Independent
Classifier: Topic :: Internet :: WWW/HTTP
Classifier: Topic :: Office/Business
License-File: LICENSE.txt
Requires-Dist: lxml
Requires-Dist: requests
Requires-Dist: requests-ntlm
Requires-Dist: requests-toolbelt
